<!DOCTYPE kpartgui>
<effect tag="ladspa" library="gverb_1216.so" id="room_reverb" ladspaid="1216" type="audio">
	<name>Room Reverb</name>
	<description>LADSPA room reverb audio effect</description>
	<author>http://www.ladspa.org</author>
	<parameter type="constant" name="room" max="300" min="1" default="75">
		<name>Room size (m)</name>
	</parameter>
	<parameter type="constant" name="delay" max="300" min="1" default="7.5" factor="10">
		<name>Delay (s/10)</name>
	</parameter>
	<parameter type="constant" name="damp" max="100" min="1" default="0.5" factor="100">
		<name>Damping</name>
	</parameter>
</effect>
